Password/segments.v
module segments(
	input [3:0] bcd_in,
	output reg [0:6] bcd_out);
	
	always@(*)
	begin
		case (bcd_in)
		4'b0000: bcd_out = ~7'b1111110; // 0
		4'b0001: bcd_out = ~7'b0110000; // 1
		4'b0010: bcd_out = ~7'b1101101; // 2
		4'b0011: bcd_out = ~7'b1111001; // 3
		4'b0100: bcd_out = ~7'b0110011; // 4	
		4'b0101: bcd_out = ~7'b1011011; // 5
		4'b0110: bcd_out = ~7'b1011111; // 6
		4'b0111: bcd_out = ~7'b1110000; // 7
		4'b1000: bcd_out = ~7'b1111111; // 8
		4'b1001: bcd_out = ~7'b1111011; // 9
			default: bcd_out = ~7'b0000000; 
		endcase
		end
		endmodule

contador/BCD_4displays.v
module BCD_4displays #(parameter N_in = 10, N_out = 7)(
	
	input [N_in-1:0] bcd_in,
	
	output [N_out-1:0] D_un,D_de,D_cen,D_un_mi
	);
	
	wire [3:0] unidades, decenas, centenas, millares;
	
	assign unidades = bcd_in % 10;
	
	assign decenas = (bcd_in / 10) % 10;
	
	assign centenas = (bcd_in / 100) % 10;
	
	assign millares = (bcd_in / 1000) % 10;
	
	
	segments unidadess (
		.bcd_in(unidades),
		.bcd_out(D_un)
	);

	segments decenass (
		.bcd_in(decenas),
		.bcd_out(D_de)
	);

	segments centenass (
		.bcd_in(centenas),
		.bcd_out(D_cen)
	);

	segments millaress (
		.bcd_in(millares),
		.bcd_out(D_un_mi)
	);
	
endmodule

BCD_displays/BCD_4displays_tb.v
module BCD_4displays_tb #(parameter N_in = 10, N_out = 7)(
);
    reg [N_in-1:0] bcd_in;
    
    wire [N_out-1:0] D_un,D_de,D_cen,D_un_mi;
    
    
    BCD_4displays dut(
        .bcd_in(bcd_in),
        .D_un(D_un),
        .D_de(D_de),
        .D_cen(D_cen),
        .D_un_mi(D_un_mi)
    );
    
    initial begin
        repeat (1023) begin
            bcd_in = $random % 1023;
            #10;
        end
        $stop;
        $finish;
        $display("Terminado"); 
    end

    initial begin
    $monitor("bcd_in: %b, D_un: %b, D_de: %b, D_cen: %b, D_un_mi: %b", bcd_in, D_un, D_de, D_cen, D_un_mi);
end

initial begin
    $dumpfile("BCD_4displays_tb.vcd");
    $dumpvars(0, BCD_4displays_tb);
end
endmodule

BCD_displays/BCD_4displays_tb.vcd
$date
	Wed Feb 18 07:19:11 2026
$end
$version
	Icarus Verilog
$end
$timescale
	1s
$end
$scope module BCD_4displays_tb $end
$var wire 7 ! D_un_mi [6:0] $end
$var wire 7 " D_un [6:0] $end
$var wire 7 # D_de [6:0] $end
$var wire 7 $ D_cen [6:0] $end
$var parameter 32 % N_in $end
$var parameter 32 & N_out $end
$var reg 10 ' bcd_in [9:0] $end
$scope module dut $end
$var wire 10 ( bcd_in [9:0] $end
$var wire 4 ) unidades [3:0] $end
$var wire 4 * millares [3:0] $end
$var wire 4 + decenas [3:0] $end
$var wire 4 , centenas [3:0] $end
$var wire 7 - D_un_mi [6:0] $end
$var wire 7 . D_un [6:0] $end
$var wire 7 / D_de [6:0] $end
$var wire 7 0 D_cen [6:0] $end
$var parameter 32 1 N_in $end
$var parameter 32 2 N_out $end
$scope module centenass $end
$var wire 4 3 bcd_in [3:0] $end
$var reg 7 4 bcd_out [0:6] $end
$upscope $end
$scope module decenass $end
$var wire 4 5 bcd_in [3:0] $end
$var reg 7 6 bcd_out [0:6] $end
$upscope $end
$scope module millaress $end
$var wire 4 7 bcd_in [3:0] $end
$var reg 7 8 bcd_out [0:6] $end
$upscope $end
$scope module unidadess $end
$var wire 4 9 bcd_in [3:0] $end
$var reg 7 : bcd_out [0:6] $end
$upscope $end
$upscope $end
$upscope $end
$enddefinitions $end
$comment Show the parameter values. $end
$dumpall
b111 2
b1010 1
b111 &
b1010 %
$end
#0
$dumpvars
b1001100 :
b100 9
b1 8
b0 7
b1001111 6
b1 5
b100 4
b1001 3
b100 0
b1001111 /
b1001100 .
b1 -
b1001 ,
b1 +
b0 *
b100 )
b1110010010 (
b1110010010 '
b100 $
b1001111 #
b1001100 "
b1 !
$end
#10
b100100 "
b100100 .
b100100 :
b10010 #
b10010 /
b10010 6
b10010 $
b10010 0
b10010 4
b101 )
b101 9
b10 +
b10 5
b10 ,
b10 3
b11100001 '
b11100001 (
#20
b1001111 "
b1001111 .
b1001111 :
b1 #
b1 /
b1 6
b100 $
b100 0
b100 4
b1 )
b1 9
b0 +
b0 5
b1001 ,
b1001 3
b1110000101 '
b1110000101 (
#30
b1111 "
b1111 .
b1111 :
b1001100 $
b1001100 0
b1001100 4
b111 )
b111 9
b100 ,
b100 3
b110010111 '
b110010111 (
#40
b1001111 "
b1001111 .
b1001111 :
b1111 #
b1111 /
b1111 6
b1 )
b1 9
b111 +
b111 5
b111010111 '
b111010111 (
#50
b10010 "
b10010 .
b10010 :
b0 #
b0 /
b0 6
b10 )
b10 9
b1000 +
b1000 5
b111100010 '
b111100010 (
#60
b1 "
b1 .
b1 :
b100100 #
b100100 /
b100100 6
b1 $
b1 0
b1 4
b0 )
b0 9
b101 +
b101 5
b0 ,
b0 3
b110010 '
b110010 (
#70
b1001111 "
b1001111 .
b1001111 :
b10010 #
b10010 /
b10010 6
b1001111 $
b1001111 0
b1001111 4
b1 )
b1 9
b10 +
b10 5
b1 ,
b1 3
b1111001 '
b1111001 (
#80
b100 "
b100 .
b100 :
b1 #
b1 /
b1 6
b1 $
b1 0
b1 4
b1001 )
b1001 9
b0 +
b0 5
b0 ,
b0 3
b1001 '
b1001 (
#90
b1111 "
b1111 .
b1111 :
b1111 #
b1111 /
b1111 6
b0 $
b0 0
b0 4
b111 )
b111 9
b111 +
b111 5
b1000 ,
b1000 3
b1101101101 '
b1101101101 (
#100
b100 "
b100 .
b100 :
b1001100 #
b1001100 /
b1001100 6
b100100 $
b100100 0
b100100 4
b1001 )
b1001 9
b100 +
b100 5
b101 ,
b101 3
b1000100101 '
b1000100101 (
#110
b100100 "
b100100 .
b100100 :
b100000 #
b100000 /
b100000 6
b100000 $
b100000 0
b100000 4
b101 )
b101 9
b110 +
b110 5
b110 ,
b110 3
b1010011001 '
b1010011001 (
#120
b1001100 "
b1001100 .
b1001100 :
b1001111 #
b1001111 /
b1001111 6
b1001111 $
b1001111 0
b1001111 4
b100 )
b100 9
b1 +
b1 5
b1 ,
b1 3
b1110010 '
b1110010 (
#130
b1111 "
b1111 .
b1111 :
b1111 #
b1111 /
b1111 6
b0 $
b0 0
b0 4
b111 )
b111 9
b111 +
b111 5
b1000 ,
b1000 3
b1101101101 '
b1101101101 (
#140
b100100 "
b100100 .
b100100 :
b10010 #
b10010 /
b10010 6
b110 $
b110 0
b110 4
b101 )
b101 9
b10 +
b10 5
b11 ,
b11 3
b101000101 '
b101000101 (
#150
b100 #
b100 /
b100 6
b1001111 $
b1001111 0
b1001111 4
b1001 +
b1001 5
b1 ,
b1 3
b11000011 '
b11000011 (
#160
b1001100 "
b1001100 .
b1001100 :
b1001111 #
b1001111 /
b1001111 6
b10010 $
b10010 0
b10010 4
b100 )
b100 9
b1 +
b1 5
b10 ,
b10 3
b11010110 '
b11010110 (
#170
b1 "
b1 .
b1 :
b1001100 #
b1001100 /
b1001100 6
b0 )
b0 9
b100 +
b100 5
b11110000 '
b11110000 (
#180
b110 "
b110 .
b110 :
b0 #
b0 /
b0 6
b1111 $
b1111 0
b1111 4
b11 )
b11 9
b1000 +
b1000 5
b111 ,
b111 3
b1100001111 '
b1100001111 (
#190
b1 "
b1 .
b1 :
b10010 #
b10010 /
b10010 6
b0 )
b0 9
b10 +
b10 5
b1011010000 '
b1011010000 (
#200
b1111 "
b1111 .
b1111 :
b100100 #
b100100 /
b100100 6
b0 $
b0 0
b0 4
b111 )
b111 9
b101 +
b101 5
b1000 ,
b1000 3
b1101011001 '
b1101011001 (
#210
b110 #
b110 /
b110 6
b11 +
b11 5
b1101000101 '
b1101000101 (
#220
b1001111 #
b1001111 /
b1001111 6
b1001100 $
b1001100 0
b1001100 4
b1 +
b1 5
b100 ,
b100 3
b110100001 '
b110100001 (
#230
b1001100 #
b1001100 /
b1001100 6
b1111 $
b1111 0
b1111 4
b100 +
b100 5
b111 ,
b111 3
b1011101011 '
b1011101011 (
#240
b110 "
b110 .
b110 :
b0 #
b0 /
b0 6
b100100 $
b100100 0
b100100 4
b11 )
b11 9
b1000 +
b1000 5
b101 ,
b101 3
b1001000111 '
b1001000111 (
#250
b1001111 "
b1001111 .
b1001111 :
b1 #
b1 /
b1 6
b100 $
b100 0
b100 4
b1 )
b1 9
b0 +
b0 5
b1001 ,
b1001 3
b1110000101 '
b1110000101 (
#260
b100000 "
b100000 .
b100000 :
b100 #
b100 /
b100 6
b100100 $
b100100 0
b100100 4
b110 )
b110 9
b1001 +
b1001 5
b101 ,
b101 3
b1001010100 '
b1001010100 (
#270
b1 "
b1 .
b1 :
b100000 #
b100000 /
b100000 6
b0 )
b0 9
b110 +
b110 5
b1000110000 '
b1000110000 (
#280
b100 "
b100 .
b100 :
b1 #
b1 /
b1 6
b1001111 $
b1001111 0
b1001111 4
b1001 )
b1001 9
b0 +
b0 5
b1 ,
b1 3
b1101101 '
b1101101 (
#290
b100000 "
b100000 .
b100000 :
b100100 #
b100100 /
b100100 6
b0 $
b0 0
b0 4
b110 )
b110 9
b101 +
b101 5
b1000 ,
b1000 3
b1101011000 '
b1101011000 (
#300
b1001100 #
b1001100 /
b1001100 6
b110 $
b110 0
b110 4
b100 +
b100 5
b11 ,
b11 3
b101011010 '
b101011010 (
#310
b1111 "
b1111 .
b1111 :
b100000 #
b100000 /
b100000 6
b1 $
b1 0
b1 4
b111 )
b111 9
b110 +
b110 5
b0 ,
b0 3
b1000011 '
b1000011 (
#320
b10010 "
b10010 .
b10010 :
b110 #
b110 /
b110 6
b110 $
b110 0
b110 4
b10 )
b10 9
b11 +
b11 5
b11 ,
b11 3
b101001100 '
b101001100 (
#330
b1001100 "
b1001100 .
b1001100 :
b1001111 #
b1001111 /
b1001111 6
b0 $
b0 0
b0 4
b100 )
b100 9
b1 +
b1 5
b1000 ,
b1000 3
b1100101110 '
b1100101110 (
#340
b100000 "
b100000 .
b100000 :
b1111 #
b1111 /
b1111 6
b10010 $
b10010 0
b10010 4
b110 )
b110 9
b111 +
b111 5
b10 ,
b10 3
b100010100 '
b100010100 (
#350
b100 "
b100 .
b100 :
b0 #
b0 /
b0 6
b1001111 $
b1001111 0
b1001111 4
b1001 )
b1001 9
b1000 +
b1000 5
b1 ,
b1 3
b10111101 '
b10111101 (
#360
b100100 "
b100100 .
b100100 :
b100100 #
b100100 /
b100100 6
b0 $
b0 0
b0 4
b101 )
b101 9
b101 +
b101 5
b1000 ,
b1000 3
b1101010111 '
b1101010111 (
#370
b0 "
b0 .
b0 :
b1 #
b1 /
b1 6
b1001100 $
b1001100 0
b1001100 4
b1000 )
b1000 9
b0 +
b0 5
b100 ,
b100 3
b110011000 '
b110011000 (
#380
b1001111 "
b1001111 .
b1001111 :
b100 $
b100 0
b100 4
b1 )
b1 9
b1001 ,
b1001 3
b1110000101 '
b1110000101 (
#390
b0 "
b0 .
b0 :
b110 #
b110 /
b110 6
b1111 $
b1111 0
b1111 4
b1000 )
b1000 9
b11 +
b11 5
b111 ,
b111 3
b1011100010 '
b1011100010 (
#400
b100 "
b100 .
b100 :
b0 #
b0 /
b0 6
b1001111 $
b1001111 0
b1001111 4
b1001 )
b1001 9
b1000 +
b1000 5
b1 ,
b1 3
b10111101 '
b10111101 (
#410
b0 "
b0 .
b0 :
b1111 #
b1111 /
b1111 6
b1111 $
b1111 0
b1111 4
b1000 )
b1000 9
b111 +
b111 5
b111 ,
b111 3
b1100001010 '
b1100001010 (
#420
b100000 "
b100000 .
b100000 :
b100 #
b100 /
b100 6
b100 $
b100 0
b100 4
b110 )
b110 9
b1001 +
b1001 5
b1001 ,
b1001 3
b1111100100 '
b1111100100 (
#430
b100100 "
b100100 .
b100100 :
b110 #
b110 /
b110 6
b1001100 $
b1001100 0
b1001100 4
b101 )
b101 9
b11 +
b11 5
b100 ,
b100 3
b110110011 '
b110110011 (
#440
b100 "
b100 .
b100 :
b1001111 #
b1001111 /
b1001111 6
b100100 $
b100100 0
b100100 4
b1001 )
b1001 9
b1 +
b1 5
b101 ,
b101 3
b1000000111 '
b1000000111 (
#450
b1 "
b1 .
b1 :
b0 #
b0 /
b0 6
b100000 $
b100000 0
b100000 4
b0 )
b0 9
b1000 +
b1000 5
b110 ,
b110 3
b1010101000 '
b1010101000 (
#460
b100100 "
b100100 .
b100100 :
b1001100 #
b1001100 /
b1001100 6
b0 $
b0 0
b0 4
b101 )
b101 9
b100 +
b100 5
b1000 ,
b1000 3
b1101001101 '
b1101001101 (
#470
b1111 "
b1111 .
b1111 :
b100 $
b100 0
b100 4
b111 )
b111 9
b1001 ,
b1001 3
b1110110011 '
b1110110011 (
#480
b1001100 "
b1001100 .
b1001100 :
b0 #
b0 /
b0 6
b1001100 $
b1001100 0
b1001100 4
b100 )
b100 9
b1000 +
b1000 5
b100 ,
b100 3
b111100100 '
b111100100 (
#490
b100100 "
b100100 .
b100100 :
b10010 #
b10010 /
b10010 6
b100000 $
b100000 0
b100000 4
b101 )
b101 9
b10 +
b10 5
b110 ,
b110 3
b1001110001 '
b1001110001 (
#500
b110 "
b110 .
b110 :
b100100 #
b100100 /
b100100 6
b100 $
b100 0
b100 4
b11 )
b11 9
b101 +
b101 5
b1001 ,
b1001 3
b1110111001 '
b1110111001 (
#510
b1001100 "
b1001100 .
b1001100 :
b1111 #
b1111 /
b1111 6
b110 $
b110 0
b110 4
b100 )
b100 9
b111 +
b111 5
b11 ,
b11 3
b101110110 '
b101110110 (
#520
b110 #
b110 /
b110 6
b100000 $
b100000 0
b100000 4
b11 +
b11 5
b110 ,
b110 3
b1001111010 '
b1001111010 (
#530
b0 "
b0 .
b0 :
b1001111 #
b1001111 /
b1001111 6
b1000 )
b1000 9
b1 +
b1 5
b1001101010 '
b1001101010 (
#540
b1111 "
b1111 .
b1111 :
b0 #
b0 /
b0 6
b0 $
b0 0
b0 4
b111 )
b111 9
b1000 +
b1000 5
b1000 ,
b1000 3
b1101110111 '
b1101110111 (
#550
b10010 "
b10010 .
b10010 :
b1001100 #
b1001100 /
b1001100 6
b110 $
b110 0
b110 4
b10 )
b10 9
b100 +
b100 5
b11 ,
b11 3
b101010110 '
b101010110 (
#560
b100100 #
b100100 /
b100100 6
b100000 $
b100000 0
b100000 4
b101 +
b101 5
b110 ,
b110 3
b1010001100 '
b1010001100 (
#570
b1001111 "
b1001111 .
b1001111 :
b1 #
b1 /
b1 6
b1 $
b1 0
b1 4
b1 )
b1 9
b0 +
b0 5
b0 ,
b0 3
b1 '
b1 (
#580
b10010 "
b10010 .
b10010 :
b100000 #
b100000 /
b100000 6
b1111 $
b1111 0
b1111 4
b10 )
b10 9
b110 +
b110 5
b111 ,
b111 3
b1011111010 '
b1011111010 (
#590
b110 "
b110 .
b110 :
b1001111 #
b1001111 /
b1001111 6
b100000 $
b100000 0
b100000 4
b11 )
b11 9
b1 +
b1 5
b110 ,
b110 3
b1001100101 '
b1001100101 (
#600
b1001100 "
b1001100 .
b1001100 :
b0 #
b0 /
b0 6
b1001100 $
b1001100 0
b1001100 4
b100 )
b100 9
b1000 +
b1000 5
b100 ,
b100 3
b111100100 '
b111100100 (
#610
b100000 "
b100000 .
b100000 :
b10010 #
b10010 /
b10010 6
b100000 $
b100000 0
b100000 4
b110 )
b110 9
b10 +
b10 5
b110 ,
b110 3
b1001110010 '
b1001110010 (
#620
b0 "
b0 .
b0 :
b1111 #
b1111 /
b1111 6
b1 $
b1 0
b1 4
b1000 )
b1000 9
b111 +
b111 5
b0 ,
b0 3
b1001110 '
b1001110 (
#630
b1001111 "
b1001111 .
b1001111 :
b1 #
b1 /
b1 6
b1001111 !
b1001111 -
b1001111 8
b1 )
b1 9
b0 +
b0 5
b1 *
b1 7
b1111101001 '
b1111101001 (
#640
b0 #
b0 /
b0 6
b100100 $
b100100 0
b100100 4
b1 !
b1 -
b1 8
b1000 +
b1000 5
b101 ,
b101 3
b0 *
b0 7
b1001000101 '
b1001000101 (
#650
b1 "
b1 .
b1 :
b1 #
b1 /
b1 6
b1001111 $
b1001111 0
b1001111 4
b0 )
b0 9
b0 +
b0 5
b1 ,
b1 3
b1100100 '
b1100100 (
#660
b110 "
b110 .
b110 :
b110 $
b110 0
b110 4
b11 )
b11 9
b11 ,
b11 3
b100101111 '
b100101111 (
#670
b100000 #
b100000 /
b100000 6
b100000 $
b100000 0
b100000 4
b110 +
b110 5
b110 ,
b110 3
b1010010111 '
b1010010111 (
#680
b0 "
b0 .
b0 :
b10010 #
b10010 /
b10010 6
b0 $
b0 0
b0 4
b1000 )
b1000 9
b10 +
b10 5
b1000 ,
b1000 3
b1100111100 '
b1100111100 (
#690
b1001100 "
b1001100 .
b1001100 :
b100 #
b100 /
b100 6
b100100 $
b100100 0
b100100 4
b100 )
b100 9
b1001 +
b1001 5
b101 ,
b101 3
b1001010010 '
b1001010010 (
#700
b1111 "
b1111 .
b1111 :
b0 #
b0 /
b0 6
b1001100 $
b1001100 0
b1001100 4
b111 )
b111 9
b1000 +
b1000 5
b100 ,
b100 3
b111100111 '
b111100111 (
#710
b100 "
b100 .
b100 :
b110 #
b110 /
b110 6
b1001 )
b1001 9
b11 +
b11 5
b110110111 '
b110110111 (
#720
b10010 "
b10010 .
b10010 :
b10010 #
b10010 /
b10010 6
b0 $
b0 0
b0 4
b10 )
b10 9
b10 +
b10 5
b1000 ,
b1000 3
b1100110110 '
b1100110110 (
#730
b1001100 "
b1001100 .
b1001100 :
b1001111 #
b1001111 /
b1001111 6
b100 )
b100 9
b1 +
b1 5
b1100101110 '
b1100101110 (
#740
b1001111 "
b1001111 .
b1001111 :
b100100 #
b100100 /
b100100 6
b1111 $
b1111 0
b1111 4
b1 )
b1 9
b101 +
b101 5
b111 ,
b111 3
b1011101111 '
b1011101111 (
#750
b100000 "
b100000 .
b100000 :
b1001111 #
b1001111 /
b1001111 6
b1001111 $
b1001111 0
b1001111 4
b110 )
b110 9
b1 +
b1 5
b1 ,
b1 3
b1110100 '
b1110100 (
#760
b100 "
b100 .
b100 :
b100 #
b100 /
b100 6
b10010 $
b10010 0
b10010 4
b1001 )
b1001 9
b1001 +
b1001 5
b10 ,
b10 3
b100101011 '
b100101011 (
#770
b1 "
b1 .
b1 :
b100000 #
b100000 /
b100000 6
b1001100 $
b1001100 0
b1001100 4
b0 )
b0 9
b110 +
b110 5
b100 ,
b100 3
b111001100 '
b111001100 (
#780
b1111 "
b1111 .
b1111 :
b1111 #
b1111 /
b1111 6
b1001111 $
b1001111 0
b1001111 4
b111 )
b111 9
b111 +
b111 5
b1 ,
b1 3
b10110001 '
b10110001 (
#790
b1 "
b1 .
b1 :
b0 #
b0 /
b0 6
b100000 $
b100000 0
b100000 4
b0 )
b0 9
b1000 +
b1000 5
b110 ,
b110 3
b1010101000 '
b1010101000 (
#800
b1001111 "
b1001111 .
b1001111 :
b100100 #
b100100 /
b100100 6
b100100 $
b100100 0
b100100 4
b1 )
b1 9
b101 +
b101 5
b101 ,
b101 3
b1000100111 '
b1000100111 (
#810
b100 "
b100 .
b100 :
b100000 #
b100000 /
b100000 6
b0 $
b0 0
b0 4
b1001 )
b1001 9
b110 +
b110 5
b1000 ,
b1000 3
b1101100101 '
b1101100101 (
#820
b10010 "
b10010 .
b10010 :
b110 #
b110 /
b110 6
b1 $
b1 0
b1 4
b10 )
b10 9
b11 +
b11 5
b0 ,
b0 3
b100000 '
b100000 (
#830
b100000 "
b100000 .
b100000 :
b1001100 #
b1001100 /
b1001100 6
b100100 $
b100100 0
b100100 4
b110 )
b110 9
b100 +
b100 5
b101 ,
b101 3
b1000100010 '
b1000100010 (
#840
b100 "
b100 .
b100 :
b110 #
b110 /
b110 6
b0 $
b0 0
b0 4
b1001 )
b1001 9
b11 +
b11 5
b1000 ,
b1000 3
b1101000111 '
b1101000111 (
#850
b1 "
b1 .
b1 :
b10010 #
b10010 /
b10010 6
b10010 $
b10010 0
b10010 4
b0 )
b0 9
b10 +
b10 5
b10 ,
b10 3
b11011100 '
b11011100 (
#860
b100 "
b100 .
b100 :
b1001100 #
b1001100 /
b1001100 6
b1001111 $
b1001111 0
b1001111 4
b1001 )
b1001 9
b100 +
b100 5
b1 ,
b1 3
b10010101 '
b10010101 (
#870
b1111 "
b1111 .
b1111 :
b1001111 #
b1001111 /
b1001111 6
b1111 $
b1111 0
b1111 4
b111 )
b111 9
b1 +
b1 5
b111 ,
b111 3
b1011001101 '
b1011001101 (
#880
b100 "
b100 .
b100 :
b1 #
b1 /
b1 6
b1 $
b1 0
b1 4
b1001 )
b1001 9
b0 +
b0 5
b0 ,
b0 3
b1001 '
b1001 (
#890
b10010 "
b10010 .
b10010 :
b10010 #
b10010 /
b10010 6
b100100 $
b100100 0
b100100 4
b10 )
b10 9
b10 +
b10 5
b101 ,
b101 3
b1000001010 '
b1000001010 (
#900
b100 "
b100 .
b100 :
b1 #
b1 /
b1 6
b1111 $
b1111 0
b1111 4
b1001 )
b1001 9
b0 +
b0 5
b111 ,
b111 3
b1011000101 '
b1011000101 (
#910
b100 #
b100 /
b100 6
b100 $
b100 0
b100 4
b1001 +
b1001 5
b1001 ,
b1001 3
b1111100111 '
b1111100111 (
#920
b10010 #
b10010 /
b10010 6
b1111 $
b1111 0
b1111 4
b10 +
b10 5
b111 ,
b111 3
b1011011001 '
b1011011001 (
#930
b1 "
b1 .
b1 :
b110 #
b110 /
b110 6
b1001100 $
b1001100 0
b1001100 4
b0 )
b0 9
b11 +
b11 5
b100 ,
b100 3
b110101110 '
b110101110 (
#940
b10010 "
b10010 .
b10010 :
b1111 #
b1111 /
b1111 6
b100100 $
b100100 0
b100100 4
b10 )
b10 9
b111 +
b111 5
b101 ,
b101 3
b1000111100 '
b1000111100 (
#950
b100000 "
b100000 .
b100000 :
b100 #
b100 /
b100 6
b0 $
b0 0
b0 4
b110 )
b110 9
b1001 +
b1001 5
b1000 ,
b1000 3
b1110000000 '
b1110000000 (
#960
b10010 "
b10010 .
b10010 :
b1001111 $
b1001111 0
b1001111 4
b10 )
b10 9
b1 ,
b1 3
b11000000 '
b11000000 (
#970
b1001111 #
b1001111 /
b1001111 6
b1 +
b1 5
b1110000 '
b1110000 (
#980
b1001111 "
b1001111 .
b1001111 :
b100100 $
b100100 0
b100100 4
b1 )
b1 9
b101 ,
b101 3
b111111111 '
b111111111 (
#990
b1111 "
b1111 .
b1111 :
b1001100 #
b1001100 /
b1001100 6
b110 $
b110 0
b110 4
b111 )
b111 9
b100 +
b100 5
b11 ,
b11 3
b101011011 '
b101011011 (
#1000
b100 "
b100 .
b100 :
b1001111 #
b1001111 /
b1001111 6
b1111 $
b1111 0
b1111 4
b1001 )
b1001 9
b1 +
b1 5
b111 ,
b111 3
b1011001111 '
b1011001111 (
#1010
b1001111 "
b1001111 .
b1001111 :
b1 #
b1 /
b1 6
b1001111 $
b1001111 0
b1001111 4
b1 )
b1 9
b0 +
b0 5
b1 ,
b1 3
b1100101 '
b1100101 (
#1020
b110 "
b110 .
b110 :
b110 #
b110 /
b110 6
b10010 $
b10010 0
b10010 4
b11 )
b11 9
b11 +
b11 5
b10 ,
b10 3
b11101001 '
b11101001 (
#1030
b1001100 "
b1001100 .
b1001100 :
b100 $
b100 0
b100 4
b100 )
b100 9
b1001 ,
b1001 3
b1110100110 '
b1110100110 (
#1040
b10010 "
b10010 .
b10010 :
b0 #
b0 /
b0 6
b0 $
b0 0
b0 4
b10 )
b10 9
b1000 +
b1000 5
b1000 ,
b1000 3
b1101110010 '
b1101110010 (
#1050
b100000 "
b100000 .
b100000 :
b110 #
b110 /
b110 6
b1001111 $
b1001111 0
b1001111 4
b110 )
b110 9
b11 +
b11 5
b1 ,
b1 3
b10001000 '
b10001000 (
#1060
b0 "
b0 .
b0 :
b100 #
b100 /
b100 6
b0 $
b0 0
b0 4
b1000 )
b1000 9
b1001 +
b1001 5
b1000 ,
b1000 3
b1110000010 '
b1110000010 (
#1070
b1001111 "
b1001111 .
b1001111 :
b1 )
b1 9
b1101111011 '
b1101111011 (
#1080
b10010 #
b10010 /
b10010 6
b10 +
b10 5
b1100110101 '
b1100110101 (
#1090
b1001100 "
b1001100 .
b1001100 :
b1 #
b1 /
b1 6
b10010 $
b10010 0
b10010 4
b100 )
b100 9
b0 +
b0 5
b10 ,
b10 3
b11001100 '
b11001100 (
#1100
b1111 "
b1111 .
b1111 :
b1001100 #
b1001100 /
b1001100 6
b1001111 $
b1001111 0
b1001111 4
b111 )
b111 9
b100 +
b100 5
b1 ,
b1 3
b10010011 '
b10010011 (
#1110
b100 "
b100 .
b100 :
b100000 #
b100000 /
b100000 6
b1001 )
b1001 9
b110 +
b110 5
b10101001 '
b10101001 (
#1120
b0 "
b0 .
b0 :
b1001111 #
b1001111 /
b1001111 6
b1 $
b1 0
b1 4
b1000 )
b1000 9
b1 +
b1 5
b0 ,
b0 3
b10010 '
b10010 (
#1130
b100100 "
b100100 .
b100100 :
b1001100 #
b1001100 /
b1001100 6
b10010 $
b10010 0
b10010 4
b101 )
b101 9
b100 +
b100 5
b10 ,
b10 3
b11110101 '
b11110101 (
#1140
b1001111 "
b1001111 .
b1001111 :
b0 #
b0 /
b0 6
b0 $
b0 0
b0 4
b1 )
b1 9
b1000 +
b1000 5
b1000 ,
b1000 3
b1101110001 '
b1101110001 (
#1150
b100000 "
b100000 .
b100000 :
b10010 #
b10010 /
b10010 6
b1001100 $
b1001100 0
b1001100 4
b110 )
b110 9
b10 +
b10 5
b100 ,
b100 3
b110101010 '
b110101010 (
#1160
b100100 "
b100100 .
b100100 :
b1001111 #
b1001111 /
b1001111 6
b1 $
b1 0
b1 4
b1001111 !
b1001111 -
b1001111 8
b101 )
b101 9
b1 +
b1 5
b0 ,
b0 3
b1 *
b1 7
b1111110111 '
b1111110111 (
#1170
b1 "
b1 .
b1 :
b0 )
b0 9
b1111110010 '
b1111110010 (
#1180
b1001100 "
b1001100 .
b1001100 :
b100 #
b100 /
b100 6
b1 !
b1 -
b1 8
b100 )
b100 9
b1001 +
b1001 5
b0 *
b0 7
b1011110 '
b1011110 (
#1190
b1 "
b1 .
b1 :
b1 #
b1 /
b1 6
b1001111 $
b1001111 0
b1001111 4
b0 )
b0 9
b0 +
b0 5
b1 ,
b1 3
b1100100 '
b1100100 (
#1200
b1001100 "
b1001100 .
b1001100 :
b1001111 #
b1001111 /
b1001111 6
b100000 $
b100000 0
b100000 4
b100 )
b100 9
b1 +
b1 5
b110 ,
b110 3
b1001100110 '
b1001100110 (
#1210
b10010 "
b10010 .
b10010 :
b0 #
b0 /
b0 6
b1111 $
b1111 0
b1111 4
b10 )
b10 9
b1000 +
b1000 5
b111 ,
b111 3
b1100001110 '
b1100001110 (
#1220
b100 "
b100 .
b100 :
b110 #
b110 /
b110 6
b1001111 $
b1001111 0
b1001111 4
b1001 )
b1001 9
b11 +
b11 5
b1 ,
b1 3
b10001011 '
b10001011 (
#1230
b1 "
b1 .
b1 :
b0 #
b0 /
b0 6
b110 $
b110 0
b110 4
b0 )
b0 9
b1000 +
b1000 5
b11 ,
b11 3
b101111100 '
b101111100 (
#1240
b100 #
b100 /
b100 6
b1111 $
b1111 0
b1111 4
b1001 +
b1001 5
b111 ,
b111 3
b1100010110 '
b1100010110 (
#1250
b100000 "
b100000 .
b100000 :
b0 $
b0 0
b0 4
b110 )
b110 9
b1000 ,
b1000 3
b1110000000 '
b1110000000 (
#1260
b100 "
b100 .
b100 :
b110 $
b110 0
b110 4
b1001 )
b1001 9
b11 ,
b11 3
b110001111 '
b110001111 (
#1270
b1111 "
b1111 .
b1111 :
b0 #
b0 /
b0 6
b1001100 $
b1001100 0
b1001100 4
b111 )
b111 9
b1000 +
b1000 5
b100 ,
b100 3
b111100111 '
b111100111 (
#1280
b1001111 "
b1001111 .
b1001111 :
b100 #
b100 /
b100 6
b1 $
b1 0
b1 4
b1 )
b1 9
b1001 +
b1001 5
b0 ,
b0 3
b1011011 '
b1011011 (
#1290
b1 #
b1 /
b1 6
b1111 $
b1111 0
b1111 4
b0 +
b0 5
b111 ,
b111 3
b1010111101 '
b1010111101 (
#1300
b110 "
b110 .
b110 :
b0 #
b0 /
b0 6
b1001111 $
b1001111 0
b1001111 4
b11 )
b11 9
b1000 +
b1000 5
b1 ,
b1 3
b10110111 '
b10110111 (
#1310
b0 "
b0 .
b0 :
b0 $
b0 0
b0 4
b1000 )
b1000 9
b1000 ,
b1000 3
b1101111000 '
b1101111000 (
#1320
b1111 "
b1111 .
b1111 :
b1001100 #
b1001100 /
b1001100 6
b1 $
b1 0
b1 4
b111 )
b111 9
b100 +
b100 5
b0 ,
b0 3
b101111 '
b101111 (
#1330
b0 #
b0 /
b0 6
b10010 $
b10010 0
b10010 4
b1000 +
b1000 5
b10 ,
b10 3
b100011111 '
b100011111 (
#1340
b10010 "
b10010 .
b10010 :
b1001111 #
b1001111 /
b1001111 6
b1111 $
b1111 0
b1111 4
b10 )
b10 9
b1 +
b1 5
b111 ,
b111 3
b1011001000 '
b1011001000 (
#1350
b1001111 "
b1001111 .
b1001111 :
b100 #
b100 /
b100 6
b10010 $
b10010 0
b10010 4
b1 )
b1 9
b1001 +
b1001 5
b10 ,
b10 3
b100100011 '
b100100011 (
#1360
b10010 "
b10010 .
b10010 :
b100000 #
b100000 /
b100000 6
b100 $
b100 0
b100 4
b10 )
b10 9
b110 +
b110 5
b1001 ,
b1001 3
b1111000010 '
b1111000010 (
