Password/segments.v
module segments(
	input [3:0] bcd_in,
	output reg [0:6] bcd_out);
	
	always@(*)
	begin
		case (bcd_in)
		4'b0000: bcd_out = ~7'b1111110; // 0
		4'b0001: bcd_out = ~7'b0110000; // 1
		4'b0010: bcd_out = ~7'b1101101; // 2
		4'b0011: bcd_out = ~7'b1111001; // 3
		4'b0100: bcd_out = ~7'b0110011; // 4	
		4'b0101: bcd_out = ~7'b1011011; // 5
		4'b0110: bcd_out = ~7'b1011111; // 6
		4'b0111: bcd_out = ~7'b1110000; // 7
		4'b1000: bcd_out = ~7'b1111111; // 8
		4'b1001: bcd_out = ~7'b1111011; // 9
			default: bcd_out = ~7'b0000000; 
		endcase
		end
		endmodule

BCD_displays/segments_tb.v
module segments_tb ();
    reg [3:0] bcd_in;
    wire [6:0] bcd_out;

    segments dut (
        .bcd_in(bcd_in),
        .bcd_out(bcd_out)
    );

    initial begin
        repeat (16) begin
            bcd_in = $random % 16;
            #10;
        end
        $stop;
        $finish;
        $display("Terminado"); 
    end

initial begin
    $monitor("bcd_in: %b, bcd_out: %b", bcd_in, bcd_out);
end

initial begin
    $dumpfile("segments_tb.vcd");
    $dumpvars(0, segments_tb);
end
endmodule

BCD_displays/simulation/questa/segments_tb.vcd
$date
	Mon Mar  2 10:21:02 2026
$end
$version
	Questa Altera Starter FPGA Edition Version 2025.2
$end
$timescale
	1ps
$end

$scope module segments_tb $end
$var reg 4 ! bcd_in [3:0] $end
$var wire 1 " bcd_out [6] $end
$var wire 1 # bcd_out [5] $end
$var wire 1 $ bcd_out [4] $end
$var wire 1 % bcd_out [3] $end
$var wire 1 & bcd_out [2] $end
$var wire 1 ' bcd_out [1] $end
$var wire 1 ( bcd_out [0] $end

$scope module dut $end
$var wire 1 ) bcd_in [3] $end
$var wire 1 * bcd_in [2] $end
$var wire 1 + bcd_in [1] $end
$var wire 1 , bcd_in [0] $end
$var reg 7 - bcd_out [0:6] $end
$upscope $end
$upscope $end
$enddefinitions $end
#0
$dumpvars
b100 !
b1001100 -
0(
0'
1&
1%
0$
0#
1"
0,
0+
1*
0)
$end
#10
b1 !
1,
0*
b1001111 -
1(
1'
#20
b1001 !
1)
b100 -
0(
0'
0%
0"
#30
b11 !
1+
0)
b110 -
1'
#40
b1101 !
0+
1*
1)
b1111111 -
1(
1%
1$
1#
1"
#60
b101 !
0)
b100100 -
0(
0'
0%
0$
0"
#70
b10 !
0,
1+
0*
b10010 -
1'
0&
1$
0#
#80
b1 !
1,
0+
b1001111 -
1(
1&
1%
0$
1"
#90
b1101 !
1*
1)
b1111111 -
1$
1#
#100
b110 !
0,
1+
0)
b100000 -
0(
0'
0&
0%
0$
0"
#110
b1101 !
1,
0+
1)
b1111111 -
1(
1'
1&
1%
1$
1"
#130
b1100 !
0,
#140
b1001 !
1,
0*
b100 -
0(
0'
0%
0$
0#
0"
#150
b110 !
0,
1+
1*
0)
b100000 -
0&
1#
